charded/__init__.py
charded/string.py
charded-0.1.0.dist-info/METADATA
charded-0.1.0.dist-info/WHEEL
charded-0.1.0.dist-info/top_level.txt
charded-0.1.0.dist-info/RECORD
