Metadata-Version: 2.4
Name: charded
Version: 0.1.0
Summary: charded
Author-email: Alex Kalaverin <alex@kalaver.in>
Project-URL: Homepage, https://kalaver.in
Classifier: Intended Audience :: Developers
Classifier: Programming Language :: Python
Classifier: Programming Language :: Python :: 3
Classifier: Programming Language :: Python :: 3.10
Classifier: Programming Language :: Python :: 3.11
Classifier: Programming Language :: Python :: 3.12
Classifier: License :: OSI Approved :: BSD License
Classifier: Operating System :: OS Independent
Requires-Python: <3.13,>=3.10
Requires-Dist: charset-normalizer>=3.4.2
Requires-Dist: kain<0.2.0,>=0.1.3
Requires-Dist: python-magic>=0.4.27
